{
"autoplayBgm":true,"autoplayBgs":false,"battleback1Name":"","battleback2Name":"","bgm":{"name":"Town1","pan":0,"pitch":100,"volume":90},"bgs":{"name":"","pan":0,"pitch":100,"volume":90},"disableDashing":false,"displayName":"","encounterList":[],"encounterStep":30,"height":13,"note":"","parallaxLoopX":false,"parallaxLoopY":false,"parallaxName":"","parallaxShow":true,"parallaxSx":0,"parallaxSy":0,"scrollType":0,"specifyBattleback":false,"tilesetId":3,"width":17,
"data":[0,8147,8146,8146,8146,8150,1536,1536,1536,8147,8146,8146,8146,8146,8146,8150,0,0,8145,8144,8144,8144,8148,1536,1536,1536,8145,8144,8144,8144,8144,8144,8148,0,0,8145,8144,8144,8144,8148,1536,1536,1536,8145,8144,8144,8144,8144,8144,8148,0,0,8153,8152,8152,8152,8156,8147,8146,8150,8153,8152,8152,8152,8152,8152,8156,0,0,1554,1554,1554,1554,1554,8145,8144,8148,1554,1554,1554,1554,1554,1554,1554,0,0,1554,1554,1554,1554,1554,8145,8144,8148,1554,3714,3700,3700,3700,3716,1554,0,0,1554,1554,1554,1554,1554,8153,8152,8156,1554,3696,3680,3680,3680,3704,1554,0,0,1554,1554,1554,1554,1554,1554,1554,1554,1554,3696,3680,3680,3680,3704,1554,0,0,1554,1554,1554,1554,1554,1554,1554,1554,1554,3696,3680,3680,3680,3704,1554,0,0,1554,1554,1554,1554,1554,1554,1554,1554,1554,3696,3680,3680,3680,3704,1554,0,0,1554,1554,1554,1554,1554,1554,1554,1554,1554,3720,3708,3708,3708,3718,1554,0,0,1554,1554,1554,1554,1554,1554,1554,1554,1554,1554,1554,1554,1554,1554,1554,0,0,0,0,1554,1554,1554,0,0,0,0,0,0,0,0,0,0,0,0,0,0,0,0,0,0,0,0,0,0,0,0,0,0,0,0,0,0,0,0,0,0,0,0,0,0,0,0,0,0,0,0,0,0,0,0,0,0,0,0,0,0,0,0,0,0,0,0,0,0,0,0,0,0,0,0,0,0,0,0,0,0,0,0,0,0,0,0,0,0,0,0,0,0,0,0,0,0,0,0,0,0,0,0,0,0,0,0,0,0,0,0,0,0,0,0,0,0,0,0,0,0,0,0,0,0,0,0,0,0,0,0,0,0,0,0,0,0,0,0,0,0,0,0,0,0,0,0,0,0,0,0,0,0,0,0,0,0,0,0,0,0,0,0,0,0,0,0,0,0,0,0,0,0,0,0,0,0,0,0,0,0,0,0,0,0,0,0,0,0,0,0,0,0,0,0,0,0,0,0,0,0,0,0,0,0,0,0,0,0,0,0,0,0,0,0,0,0,0,0,0,0,0,0,0,0,0,0,0,0,0,0,0,0,0,0,0,0,0,0,0,0,0,0,0,0,0,0,0,0,0,0,0,0,0,0,0,0,0,0,0,0,0,0,0,0,0,0,0,0,0,0,0,0,0,0,0,0,0,0,0,0,0,0,0,0,0,0,0,0,0,0,0,0,0,0,0,0,0,0,0,0,0,0,0,0,0,0,0,0,0,0,0,0,0,0,0,0,0,0,0,0,0,0,0,0,0,0,0,0,0,0,0,0,0,0,0,0,0,0,0,0,0,0,0,0,0,0,0,0,0,0,0,0,0,0,0,0,0,0,0,0,0,0,0,0,0,0,0,0,0,0,0,0,0,0,0,0,0,0,0,0,0,0,0,0,0,0,0,0,0,0,0,0,0,0,0,0,0,0,0,0,0,0,0,0,0,0,0,0,0,0,0,0,0,0,0,0,0,0,0,0,0,0,0,0,0,0,0,0,0,0,0,0,0,0,0,0,0,0,0,0,0,0,0,0,0,0,0,0,0,0,0,0,0,0,0,0,0,0,0,0,0,0,0,0,0,0,0,0,0,0,0,0,0,0,0,0,0,0,0,0,0,0,0,0,0,0,160,134,0,0,134,0,0,0,0,0,166,167,0,0,0,0,0,168,142,0,0,142,0,0,0,0,0,0,0,0,0,0,0,0,0,0,0,0,162,0,0,0,0,112,0,0,200,0,0,0,0,0,0,81,82,0,0,0,0,0,0,0,0,200,0,0,0,0,0,0,89,90,0,0,0,0,0,0,0,0,240,0,162,0,0,0,0,0,0,0,0,0,0,0,104,96,104,0,0,0,0,0,0,0,0,0,0,0,0,0,0,0,0,0,0,0,0,0,0,0,0,0,0,0,0,0,0,0,0,0,0,0,0,0,0,0,0,0,0,0,0,0,0,0,0,0,0,0,0,0,0,0,0,0,0,0,0,0,0,0,0,0,0,0,0,0,0,0,0,0,0,0,0,0,0,0,0,0,0,0,0,0,0,0,0,0,0,0,0,0,0,0,0,0,0,0,0,0,0,0,0,0,0,0,0,0,0,0,0,0,0,0,0,0,0,0,0,5,0,0,0,0,0,0,0,0,0,0,0,0,0,0,0,0,5,0,0,0,0,0,0,0,0,0,0,0,0,0,0,0,0,0,0,0,0,0,0,0,0,0,0,0,0,0,0,0,0,0,0,0,0,5,0,0,0,0,0,0,0,0,0,0,0,0,0,0,0,0,5,0,0,0,0,0,0,0,0,0,0,0,0,0,0,0,0,5,0,0,0,0,0,0,0,0,0,0,0,0,0,0,0,0,0,0,0,0,0,0,0,0,0,0,0,0,0,0,0,0,0,0,0,0,0,0,0,0,0,0,0,0,0,0,0,0,0,0,0,0,0,0,0,0,0,0,0,0,0,0,0,0,0,0,0,0,0,0,0,0,0,0,0,0,0,0,0,0,0,0,0,0,0,0,0,0,0,0,0,0,0,0,0,0,0,0,0,0,0,0,0,0,0,0,0,0,0,0,0,0,0,0,0,0,0,0,0,0,0,0,0,0,0,0,0,0,0,0,0,0,0,0,0,0,0,0,0,0,0,0,0,0,0,0,0,0,0,0,0,0,0,0,0,0,0,0,0,0,0,0,0,0,0,0,0,0,0,0,0,0,0,0,0,0,0,0,0,0,0,0,0,0,0,0,0,0,0,0,0,0,0,0,0,0,0,0,0,0,0,0,0,0,0,0,0,0,0,0,0,0,0,0,0,0,0,0,0,0,0,0,0,0,0,0,0,0,0,0,0,0,0,0,0,0,0,0,0,0,0,0,0,0,0,0,0,0,0,0,0,0,0,0,0,0,0,0,0,0,0,0,0,0,0,0,0,0,0,0,0,0,0,0,0,0,0,0,0,0,0,0,0,0,0,0,0,0,0,0,0,0,0,0,0,0,0,0,0,0,0,0,0,0,0,0,0,0,0,0,0,0,0,0,0,0,0,0,0,0,0,0,0,0,0,0,0,0,0,0],
"events":[
null,
{"id":1,"name":"EV001","note":"","pages":[{"conditions":{"actorId":1,"actorValid":false,"itemId":1,"itemValid":false,"selfSwitchCh":"A","selfSwitchValid":false,"switch1Id":1,"switch1Valid":false,"switch2Id":1,"switch2Valid":false,"variableId":1,"variableValid":false,"variableValue":0},"directionFix":false,"image":{"characterIndex":0,"characterName":"","direction":2,"pattern":0,"tileId":0},"list":[{"code":250,"indent":0,"parameters":[{"name":"Door5","volume":90,"pitch":100,"pan":0}]},{"code":201,"indent":0,"parameters":[0,2,18,12,0,1]},{"code":0,"indent":0,"parameters":[]}],"moveFrequency":3,"moveRoute":{"list":[{"code":0,"parameters":[]}],"repeat":true,"skippable":false,"wait":false},"moveSpeed":3,"moveType":0,"priorityType":0,"stepAnime":false,"through":false,"trigger":1,"walkAnime":true}],"x":4,"y":12},
{"id":2,"name":"EV002","note":"","pages":[{"conditions":{"actorId":1,"actorValid":false,"itemId":1,"itemValid":false,"selfSwitchCh":"A","selfSwitchValid":false,"switch1Id":1,"switch1Valid":false,"switch2Id":1,"switch2Valid":false,"variableId":1,"variableValid":false,"variableValue":0},"directionFix":false,"image":{"characterIndex":0,"characterName":"","direction":2,"pattern":0,"tileId":0},"list":[{"code":250,"indent":0,"parameters":[{"name":"Door5","volume":90,"pitch":100,"pan":0}]},{"code":201,"indent":0,"parameters":[0,2,18,12,0,1]},{"code":0,"indent":0,"parameters":[]}],"moveFrequency":3,"moveRoute":{"list":[{"code":0,"parameters":[]}],"repeat":true,"skippable":false,"wait":false},"moveSpeed":3,"moveType":0,"priorityType":0,"stepAnime":false,"through":false,"trigger":1,"walkAnime":true}],"x":5,"y":12},
{"id":3,"name":"EV003","note":"","pages":[{"conditions":{"actorId":1,"actorValid":false,"itemId":1,"itemValid":false,"selfSwitchCh":"A","selfSwitchValid":false,"switch1Id":1,"switch1Valid":false,"switch2Id":1,"switch2Valid":false,"variableId":1,"variableValid":false,"variableValue":0},"directionFix":false,"image":{"characterIndex":0,"characterName":"","direction":2,"pattern":0,"tileId":0},"list":[{"code":250,"indent":0,"parameters":[{"name":"Door5","volume":90,"pitch":100,"pan":0}]},{"code":201,"indent":0,"parameters":[0,2,18,12,0,1]},{"code":0,"indent":0,"parameters":[]}],"moveFrequency":3,"moveRoute":{"list":[{"code":0,"parameters":[]}],"repeat":true,"skippable":false,"wait":false},"moveSpeed":3,"moveType":0,"priorityType":0,"stepAnime":false,"through":false,"trigger":1,"walkAnime":true}],"x":3,"y":12},
{"id":4,"name":"EV004","note":"","pages":[{"conditions":{"actorId":1,"actorValid":false,"itemId":1,"itemValid":false,"selfSwitchCh":"A","selfSwitchValid":false,"switch1Id":1,"switch1Valid":false,"switch2Id":1,"switch2Valid":false,"variableId":1,"variableValid":false,"variableValue":0},"directionFix":false,"image":{"tileId":0,"characterName":"Damage3","direction":2,"pattern":1,"characterIndex":6},"list":[{"code":101,"indent":0,"parameters":["1005701",0,0,2]},{"code":401,"indent":0,"parameters":["私が描いた絵だ"]},{"code":401,"indent":0,"parameters":[""]},{"code":401,"indent":0,"parameters":[""]},{"code":401,"indent":0,"parameters":[""]},{"code":101,"indent":0,"parameters":["1005704",0,0,2]},{"code":401,"indent":0,"parameters":["そこそこよく描けた"]},{"code":0,"indent":0,"parameters":[]}],"moveFrequency":3,"moveRoute":{"list":[{"code":0,"parameters":[]}],"repeat":true,"skippable":false,"wait":false},"moveSpeed":3,"moveType":0,"priorityType":1,"stepAnime":false,"through":false,"trigger":0,"walkAnime":true}],"x":4,"y":3},
{"id":5,"name":"EV005","note":"","pages":[{"conditions":{"actorId":1,"actorValid":false,"itemId":1,"itemValid":false,"selfSwitchCh":"A","selfSwitchValid":false,"switch1Id":1,"switch1Valid":false,"switch2Id":1,"switch2Valid":false,"variableId":1,"variableValid":false,"variableValue":0},"directionFix":false,"image":{"tileId":0,"characterName":"Damage3","direction":2,"pattern":1,"characterIndex":6},"list":[{"code":101,"indent":0,"parameters":["1005701",0,0,2]},{"code":401,"indent":0,"parameters":["私が描いた絵だ"]},{"code":401,"indent":0,"parameters":[""]},{"code":401,"indent":0,"parameters":[""]},{"code":401,"indent":0,"parameters":[""]},{"code":101,"indent":0,"parameters":["1005704",0,0,2]},{"code":401,"indent":0,"parameters":["そこそこよく描けた"]},{"code":0,"indent":0,"parameters":[]}],"moveFrequency":3,"moveRoute":{"list":[{"code":0,"parameters":[]}],"repeat":true,"skippable":false,"wait":false},"moveSpeed":3,"moveType":0,"priorityType":1,"stepAnime":false,"through":false,"trigger":0,"walkAnime":true}],"x":3,"y":3},
{"id":6,"name":"EV006","note":"","pages":[{"conditions":{"actorId":1,"actorValid":false,"itemId":1,"itemValid":false,"selfSwitchCh":"A","selfSwitchValid":false,"switch1Id":1,"switch1Valid":false,"switch2Id":1,"switch2Valid":false,"variableId":1,"variableValid":false,"variableValue":0},"directionFix":false,"image":{"tileId":0,"characterName":"Damage3","direction":6,"pattern":2,"characterIndex":5},"list":[{"code":101,"indent":0,"parameters":["1005701",0,0,2]},{"code":401,"indent":0,"parameters":["料理でもつくろうかな"]},{"code":102,"indent":0,"parameters":[["Yes","No"],1,0,1,0]},{"code":402,"indent":0,"parameters":[0,"Yes"]},{"code":314,"indent":1,"parameters":[0,0]},{"code":250,"indent":1,"parameters":[{"name":"Heal8","volume":90,"pitch":100,"pan":0}]},{"code":101,"indent":1,"parameters":["1005704",0,0,2]},{"code":401,"indent":1,"parameters":["ご飯を食べて元気いっぱい！"]},{"code":0,"indent":1,"parameters":[]},{"code":402,"indent":0,"parameters":[1,"No"]},{"code":101,"indent":1,"parameters":["1005702",0,0,2]},{"code":401,"indent":1,"parameters":["ダイエットダイエット・・・！"]},{"code":0,"indent":1,"parameters":[]},{"code":404,"indent":0,"parameters":[]},{"code":0,"indent":0,"parameters":[]}],"moveFrequency":3,"moveRoute":{"list":[{"code":0,"parameters":[]}],"repeat":true,"skippable":false,"wait":false},"moveSpeed":3,"moveType":0,"priorityType":1,"stepAnime":false,"through":false,"trigger":0,"walkAnime":true}],"x":2,"y":4},
{"id":7,"name":"EV007","note":"","pages":[{"conditions":{"actorId":1,"actorValid":false,"itemId":1,"itemValid":false,"selfSwitchCh":"A","selfSwitchValid":false,"switch1Id":1,"switch1Valid":false,"switch2Id":1,"switch2Valid":false,"variableId":1,"variableValid":false,"variableValue":0},"directionFix":false,"image":{"tileId":0,"characterName":"Damage3","direction":2,"pattern":0,"characterIndex":6},"list":[{"code":101,"indent":0,"parameters":["1005701",0,0,2]},{"code":401,"indent":0,"parameters":["時計はずっとむかしに壊れたままだ"]},{"code":0,"indent":0,"parameters":[]}],"moveFrequency":3,"moveRoute":{"list":[{"code":0,"parameters":[]}],"repeat":true,"skippable":false,"wait":false},"moveSpeed":3,"moveType":0,"priorityType":1,"stepAnime":false,"through":false,"trigger":0,"walkAnime":true}],"x":10,"y":3},
{"id":8,"name":"EV008","note":"","pages":[{"conditions":{"actorId":1,"actorValid":false,"itemId":1,"itemValid":false,"selfSwitchCh":"A","selfSwitchValid":false,"switch1Id":1,"switch1Valid":false,"switch2Id":1,"switch2Valid":false,"variableId":1,"variableValid":false,"variableValue":0},"directionFix":false,"image":{"tileId":0,"characterName":"Damage3","direction":4,"pattern":2,"characterIndex":4},"list":[{"code":250,"indent":0,"parameters":[{"name":"Decision5","volume":90,"pitch":100,"pan":0}]},{"code":101,"indent":0,"parameters":["1005704",0,0,2]},{"code":401,"indent":0,"parameters":["昔した１マナ貯金を回収した！"]},{"code":125,"indent":0,"parameters":[0,0,1]},{"code":0,"indent":0,"parameters":[]}],"moveFrequency":3,"moveRoute":{"list":[{"code":0,"parameters":[]}],"repeat":true,"skippable":false,"wait":false},"moveSpeed":3,"moveType":0,"priorityType":1,"stepAnime":false,"through":false,"trigger":0,"walkAnime":true}],"x":5,"y":5},
{"id":9,"name":"EV009","note":"","pages":[{"conditions":{"actorId":1,"actorValid":false,"itemId":1,"itemValid":false,"selfSwitchCh":"A","selfSwitchValid":false,"switch1Id":1,"switch1Valid":false,"switch2Id":1,"switch2Valid":false,"variableId":1,"variableValid":false,"variableValue":0},"directionFix":false,"image":{"characterIndex":0,"characterName":"","direction":2,"pattern":0,"tileId":0},"list":[{"code":0,"indent":0,"parameters":[]}],"moveFrequency":3,"moveRoute":{"list":[{"code":0,"parameters":[]}],"repeat":true,"skippable":false,"wait":false},"moveSpeed":3,"moveType":0,"priorityType":0,"stepAnime":false,"through":true,"trigger":0,"walkAnime":true},{"conditions":{"actorId":1,"actorValid":false,"itemId":1,"itemValid":false,"selfSwitchCh":"A","selfSwitchValid":false,"switch1Id":11,"switch1Valid":true,"switch2Id":1,"switch2Valid":false,"variableId":1,"variableValid":false,"variableValue":0},"directionFix":false,"image":{"tileId":0,"characterName":"Package1","direction":6,"pattern":0,"characterIndex":1},"list":[{"code":101,"indent":0,"parameters":["Package1",1,0,2]},{"code":401,"indent":0,"parameters":["お疲れ様、私と交代するか？"]},{"code":102,"indent":0,"parameters":[["Yes","No"],1,0,1,0]},{"code":402,"indent":0,"parameters":[0,"Yes"]},{"code":101,"indent":1,"parameters":["",0,1,2]},{"code":401,"indent":1,"parameters":["ハロルドを操作します"]},{"code":401,"indent":1,"parameters":["※クリミアもついてきてはいますが戦闘に参加しません。"]},{"code":129,"indent":1,"parameters":[1,1,false]},{"code":129,"indent":1,"parameters":[3,0,false]},{"code":101,"indent":1,"parameters":["Package1",1,0,2]},{"code":401,"indent":1,"parameters":["ワクワク。"]},{"code":401,"indent":1,"parameters":["それじゃ代わりに私の分身をおいておこう"]},{"code":121,"indent":1,"parameters":[12,12,0]},{"code":0,"indent":1,"parameters":[]},{"code":402,"indent":0,"parameters":[1,"No"]},{"code":101,"indent":1,"parameters":["Package1",1,0,2]},{"code":401,"indent":1,"parameters":["そうか。"]},{"code":0,"indent":1,"parameters":[]},{"code":404,"indent":0,"parameters":[]},{"code":0,"indent":0,"parameters":[]}],"moveFrequency":3,"moveRoute":{"list":[{"code":0,"parameters":[]}],"repeat":true,"skippable":false,"wait":false},"moveSpeed":3,"moveType":0,"priorityType":1,"stepAnime":true,"through":false,"trigger":0,"walkAnime":true},{"conditions":{"actorId":1,"actorValid":false,"itemId":1,"itemValid":false,"selfSwitchCh":"A","selfSwitchValid":false,"switch1Id":12,"switch1Valid":true,"switch2Id":1,"switch2Valid":false,"variableId":1,"variableValid":false,"variableValue":0},"directionFix":false,"image":{"tileId":0,"characterName":"Package1","direction":6,"pattern":0,"characterIndex":1},"list":[{"code":101,"indent":0,"parameters":["Package1",1,0,2]},{"code":401,"indent":0,"parameters":["お疲れ様、クリミアと交代するか？"]},{"code":102,"indent":0,"parameters":[["Yes","No"],1,0,1,0]},{"code":402,"indent":0,"parameters":[0,"Yes"]},{"code":101,"indent":1,"parameters":["",0,1,2]},{"code":401,"indent":1,"parameters":["クリミアを操作します"]},{"code":129,"indent":1,"parameters":[1,0,false]},{"code":129,"indent":1,"parameters":[3,1,false]},{"code":101,"indent":1,"parameters":["Package1",1,0,2]},{"code":401,"indent":1,"parameters":["お疲れ様。"]},{"code":121,"indent":1,"parameters":[12,12,1]},{"code":0,"indent":1,"parameters":[]},{"code":402,"indent":0,"parameters":[1,"No"]},{"code":101,"indent":1,"parameters":["Package1",1,0,2]},{"code":401,"indent":1,"parameters":["そうか。"]},{"code":0,"indent":1,"parameters":[]},{"code":404,"indent":0,"parameters":[]},{"code":0,"indent":0,"parameters":[]}],"moveFrequency":3,"moveRoute":{"list":[{"code":0,"parameters":[]}],"repeat":true,"skippable":false,"wait":false},"moveSpeed":3,"moveType":0,"priorityType":1,"stepAnime":true,"through":false,"trigger":0,"walkAnime":true},{"conditions":{"actorId":1,"actorValid":false,"itemId":1,"itemValid":false,"selfSwitchCh":"A","selfSwitchValid":false,"switch1Id":14,"switch1Valid":true,"switch2Id":11,"switch2Valid":true,"variableId":1,"variableValid":false,"variableValue":0},"directionFix":false,"image":{"tileId":0,"characterName":"Package1","direction":6,"pattern":0,"characterIndex":1},"list":[{"code":101,"indent":0,"parameters":["Package1",1,0,2]},{"code":401,"indent":0,"parameters":["交代するならクリミアを呼んできてくれ"]},{"code":0,"indent":0,"parameters":[]}],"moveFrequency":3,"moveRoute":{"list":[{"code":0,"parameters":[]}],"repeat":true,"skippable":false,"wait":false},"moveSpeed":3,"moveType":0,"priorityType":1,"stepAnime":true,"through":false,"trigger":0,"walkAnime":true}],"x":2,"y":7},
{"id":10,"name":"EV010","note":"","pages":[{"conditions":{"actorId":1,"actorValid":false,"itemId":1,"itemValid":false,"selfSwitchCh":"A","selfSwitchValid":false,"switch1Id":1,"switch1Valid":false,"switch2Id":1,"switch2Valid":false,"variableId":1,"variableValid":false,"variableValue":0},"directionFix":false,"image":{"characterIndex":0,"characterName":"","direction":2,"pattern":0,"tileId":0},"list":[{"code":0,"indent":0,"parameters":[]}],"moveFrequency":3,"moveRoute":{"list":[{"code":0,"parameters":[]}],"repeat":true,"skippable":false,"wait":false},"moveSpeed":3,"moveType":0,"priorityType":0,"stepAnime":false,"through":true,"trigger":0,"walkAnime":true},{"conditions":{"actorId":1,"actorValid":false,"itemId":1,"itemValid":false,"selfSwitchCh":"A","selfSwitchValid":false,"switch1Id":13,"switch1Valid":true,"switch2Id":1,"switch2Valid":false,"variableId":1,"variableValid":false,"variableValue":0},"directionFix":false,"image":{"tileId":0,"characterName":"saijyaku","direction":4,"pattern":0,"characterIndex":0},"list":[{"code":101,"indent":0,"parameters":["saijyaku",0,0,2]},{"code":401,"indent":0,"parameters":["お疲れ様、あたしと交代する？"]},{"code":102,"indent":0,"parameters":[["Yes","No"],1,0,1,0]},{"code":402,"indent":0,"parameters":[0,"Yes"]},{"code":101,"indent":1,"parameters":["",0,1,2]},{"code":401,"indent":1,"parameters":["モニアを操作します"]},{"code":401,"indent":1,"parameters":["※クリミアもついてきてはいますが戦闘に参加しません。"]},{"code":129,"indent":1,"parameters":[1,1,false]},{"code":129,"indent":1,"parameters":[4,0,false]},{"code":101,"indent":1,"parameters":["saijyaku",0,0,2]},{"code":401,"indent":1,"parameters":["やったね！それじゃわたしの代わりの人形"]},{"code":401,"indent":1,"parameters":["置いとくよ！"]},{"code":121,"indent":1,"parameters":[14,14,0]},{"code":0,"indent":1,"parameters":[]},{"code":402,"indent":0,"parameters":[1,"No"]},{"code":101,"indent":1,"parameters":["saijyaku",0,0,2]},{"code":401,"indent":1,"parameters":["ちぇ～"]},{"code":0,"indent":1,"parameters":[]},{"code":404,"indent":0,"parameters":[]},{"code":0,"indent":0,"parameters":[]}],"moveFrequency":3,"moveRoute":{"list":[{"code":0,"parameters":[]}],"repeat":true,"skippable":false,"wait":false},"moveSpeed":3,"moveType":0,"priorityType":1,"stepAnime":true,"through":false,"trigger":0,"walkAnime":true},{"conditions":{"actorId":1,"actorValid":false,"itemId":1,"itemValid":false,"selfSwitchCh":"A","selfSwitchValid":false,"switch1Id":14,"switch1Valid":true,"switch2Id":1,"switch2Valid":false,"variableId":1,"variableValid":false,"variableValue":0},"directionFix":false,"image":{"tileId":0,"characterName":"saijyaku","direction":4,"pattern":0,"characterIndex":0},"list":[{"code":101,"indent":0,"parameters":["saijyaku",0,0,2]},{"code":401,"indent":0,"parameters":["お疲れ様、クリミアと交代する？"]},{"code":102,"indent":0,"parameters":[["Yes","No"],1,0,1,0]},{"code":402,"indent":0,"parameters":[0,"Yes"]},{"code":101,"indent":1,"parameters":["",0,1,2]},{"code":401,"indent":1,"parameters":["クリミアを操作します"]},{"code":129,"indent":1,"parameters":[1,0,false]},{"code":129,"indent":1,"parameters":[4,1,false]},{"code":101,"indent":1,"parameters":["saijyaku",0,0,2]},{"code":401,"indent":1,"parameters":["お疲れ様。"]},{"code":121,"indent":1,"parameters":[14,14,1]},{"code":0,"indent":1,"parameters":[]},{"code":402,"indent":0,"parameters":[1,"No"]},{"code":101,"indent":1,"parameters":["saijyaku",0,0,2]},{"code":401,"indent":1,"parameters":["よしよしっ"]},{"code":0,"indent":1,"parameters":[]},{"code":404,"indent":0,"parameters":[]},{"code":0,"indent":0,"parameters":[]}],"moveFrequency":3,"moveRoute":{"list":[{"code":0,"parameters":[]}],"repeat":true,"skippable":false,"wait":false},"moveSpeed":3,"moveType":0,"priorityType":1,"stepAnime":true,"through":false,"trigger":0,"walkAnime":true},{"conditions":{"actorId":1,"actorValid":false,"itemId":1,"itemValid":false,"selfSwitchCh":"A","selfSwitchValid":false,"switch1Id":12,"switch1Valid":true,"switch2Id":13,"switch2Valid":true,"variableId":1,"variableValid":false,"variableValue":0},"directionFix":false,"image":{"tileId":0,"characterName":"saijyaku","direction":4,"pattern":0,"characterIndex":0},"list":[{"code":101,"indent":0,"parameters":["saijyaku",0,0,2]},{"code":401,"indent":0,"parameters":["交代するならクリミアを呼んできて！"]},{"code":0,"indent":0,"parameters":[]}],"moveFrequency":3,"moveRoute":{"list":[{"code":0,"parameters":[]}],"repeat":true,"skippable":false,"wait":false},"moveSpeed":3,"moveType":0,"priorityType":1,"stepAnime":true,"through":false,"trigger":0,"walkAnime":true}],"x":4,"y":7},
{"id":11,"name":"EV011","note":"","pages":[{"conditions":{"actorId":1,"actorValid":false,"itemId":1,"itemValid":false,"selfSwitchCh":"A","selfSwitchValid":false,"switch1Id":1,"switch1Valid":false,"switch2Id":1,"switch2Valid":false,"variableId":1,"variableValid":false,"variableValue":0},"directionFix":false,"image":{"tileId":0,"characterName":"Damage3","direction":2,"pattern":0,"characterIndex":5},"list":[{"code":101,"indent":0,"parameters":["",0,0,2]},{"code":401,"indent":0,"parameters":["スタッフロールが書いてある"]},{"code":401,"indent":0,"parameters":["(※都合上見辛いものになってます。すみません・・・。)"]},{"code":101,"indent":0,"parameters":["",0,0,2]},{"code":401,"indent":0,"parameters":["見ますか？"]},{"code":102,"indent":0,"parameters":[["Yes","No"],1,0,1,0]},{"code":402,"indent":0,"parameters":[0,"Yes"]},{"code":101,"indent":1,"parameters":["",0,1,1]},{"code":401,"indent":1,"parameters":["　　　　　　　　　   BossSurvivorHS"]},{"code":401,"indent":1,"parameters":[""]},{"code":401,"indent":1,"parameters":["　　　　　　　エグゼクティブプロデューサー"]},{"code":401,"indent":1,"parameters":["　　　　　　　　　　　 むじゅ"]},{"code":101,"indent":1,"parameters":["",0,1,1]},{"code":401,"indent":1,"parameters":[""]},{"code":401,"indent":1,"parameters":["　 　　　　　　　　　ディレクター"]},{"code":401,"indent":1,"parameters":["　　　　　　　　　　　 むじゅ"]},{"code":401,"indent":1,"parameters":[""]},{"code":101,"indent":1,"parameters":["",0,1,1]},{"code":401,"indent":1,"parameters":["　　　　　　　 スーパーメディアクリエータ"]},{"code":401,"indent":1,"parameters":["　　　　　　　　　　　 むじゅ"]},{"code":401,"indent":1,"parameters":[""]},{"code":401,"indent":1,"parameters":["　　　　　　　　　　　　企画"]},{"code":101,"indent":1,"parameters":["",0,1,1]},{"code":401,"indent":1,"parameters":["　　　　　　　　　　　 むじゅ"]},{"code":401,"indent":1,"parameters":[""]},{"code":401,"indent":1,"parameters":["　　　　　　　　　　　　制作"]},{"code":401,"indent":1,"parameters":["　　　　　　　　　　　 むじゅ"]},{"code":101,"indent":1,"parameters":["",0,1,1]},{"code":401,"indent":1,"parameters":[""]},{"code":401,"indent":1,"parameters":["　　　　　　　　　　　イラスト"]},{"code":401,"indent":1,"parameters":["　　　　　　　ＲＰＧツクールＭＶ公式のやつ"]},{"code":401,"indent":1,"parameters":[""]},{"code":101,"indent":1,"parameters":["",0,1,1]},{"code":401,"indent":1,"parameters":["　　　　　　　　　　  使用ツール"]},{"code":401,"indent":1,"parameters":["　　　　　　　　　ＲＰＧツクールＭＶ"]},{"code":401,"indent":1,"parameters":[""]},{"code":401,"indent":1,"parameters":["                      プラグイン"]},{"code":101,"indent":1,"parameters":["",0,1,1]},{"code":401,"indent":1,"parameters":["　　　　　　　　CompareParamRefine　　　　"]},{"code":401,"indent":1,"parameters":["                    トリアコンタンさん"]},{"code":401,"indent":1,"parameters":[""]},{"code":401,"indent":1,"parameters":["　　　　　　　　YEP_CoreEngine"]},{"code":101,"indent":1,"parameters":["",0,1,1]},{"code":401,"indent":1,"parameters":["　　　　　　　　YEP_BattleStatusWindow"]},{"code":401,"indent":1,"parameters":["　　　　　　　　YEP_BattleEngineCore"]},{"code":401,"indent":1,"parameters":["　　　　　　　　YEP_ItemCore"]},{"code":401,"indent":1,"parameters":["　　　　　　　　YEP_X_ItemUpgradeSlots"]},{"code":101,"indent":1,"parameters":["",0,1,1]},{"code":401,"indent":1,"parameters":["                     Yanfly Engineさん"]},{"code":401,"indent":1,"parameters":["　　　　　　　　"]},{"code":401,"indent":1,"parameters":["　　　　　　　　sai_Scenefile"]},{"code":401,"indent":1,"parameters":["　　　　　　　　　　　sairiさん"]},{"code":101,"indent":1,"parameters":["",0,1,1]},{"code":401,"indent":1,"parameters":[""]},{"code":401,"indent":1,"parameters":["　　　　　　　　T_dashMotion"]},{"code":401,"indent":1,"parameters":["　　　　　　　　　　　Trbさん"]},{"code":401,"indent":1,"parameters":[""]},{"code":101,"indent":1,"parameters":["",0,1,1]},{"code":401,"indent":1,"parameters":["　　　　　　　　OriginalTimer"]},{"code":401,"indent":1,"parameters":["　　　　　　　　　　　fftfanttさん"]},{"code":401,"indent":1,"parameters":[""]},{"code":401,"indent":1,"parameters":[""]},{"code":101,"indent":1,"parameters":["",0,1,1]},{"code":401,"indent":1,"parameters":["　　　　　　　　　 スペシャルサンクス"]},{"code":401,"indent":1,"parameters":["　　　　　　　　　　 デバッグ　MGC コジロー"]},{"code":401,"indent":1,"parameters":[""]},{"code":401,"indent":1,"parameters":["　　　　　　　　　　"]},{"code":101,"indent":1,"parameters":["",0,1,1]},{"code":401,"indent":1,"parameters":["　　　　　　　Thank you for your　playing!"]},{"code":0,"indent":1,"parameters":[]},{"code":402,"indent":0,"parameters":[1,"No"]},{"code":0,"indent":1,"parameters":[]},{"code":404,"indent":0,"parameters":[]},{"code":0,"indent":0,"parameters":[]}],"moveFrequency":3,"moveRoute":{"list":[{"code":0,"parameters":[]}],"repeat":true,"skippable":false,"wait":false},"moveSpeed":3,"moveType":0,"priorityType":1,"stepAnime":false,"through":false,"trigger":0,"walkAnime":true}],"x":14,"y":3},
{"id":12,"name":"EV012","note":"","pages":[{"conditions":{"actorId":1,"actorValid":false,"itemId":1,"itemValid":false,"selfSwitchCh":"A","selfSwitchValid":false,"switch1Id":13,"switch1Valid":false,"switch2Id":1,"switch2Valid":false,"variableId":1,"variableValid":false,"variableValue":0},"directionFix":false,"image":{"tileId":0,"characterName":"Damage3","direction":4,"pattern":0,"characterIndex":5},"list":[{"code":101,"indent":0,"parameters":["",0,0,2]},{"code":401,"indent":0,"parameters":["この世のレア装備について"]},{"code":401,"indent":0,"parameters":[""]},{"code":401,"indent":0,"parameters":[""]},{"code":401,"indent":0,"parameters":["読みますか？"]},{"code":102,"indent":0,"parameters":[["Yes","No"],1,0,2,0]},{"code":402,"indent":0,"parameters":[0,"Yes"]},{"code":101,"indent":1,"parameters":["",0,0,2]},{"code":401,"indent":1,"parameters":["○各女神（とペット）のドロップ品"]},{"code":401,"indent":1,"parameters":["獣人のシューズ　森の島　20%"]},{"code":401,"indent":1,"parameters":["エレメントフルメイル　氷の迷宮　10%"]},{"code":401,"indent":1,"parameters":["アシュリー　雷の谷　1%"]},{"code":101,"indent":1,"parameters":["",0,0,2]},{"code":401,"indent":1,"parameters":["※これらは天界だと確率が跳ね上がります"]},{"code":101,"indent":1,"parameters":["",0,0,2]},{"code":401,"indent":1,"parameters":["大天使の代理役のゴーラー　???????? ３３％"]},{"code":401,"indent":1,"parameters":["終焉を観る者　?????　３３％"]},{"code":401,"indent":1,"parameters":["終焉を喰らう者　??????　３３％"]},{"code":0,"indent":1,"parameters":[]},{"code":402,"indent":0,"parameters":[1,"No"]},{"code":0,"indent":1,"parameters":[]},{"code":404,"indent":0,"parameters":[]},{"code":0,"indent":0,"parameters":[]}],"moveFrequency":3,"moveRoute":{"list":[{"code":0,"parameters":[]}],"repeat":true,"skippable":false,"wait":false},"moveSpeed":3,"moveType":0,"priorityType":1,"stepAnime":false,"through":false,"trigger":0,"walkAnime":true}],"x":7,"y":6},
null
]
}